setup.py
nimscommon/__init__.py
nimscommon.egg-info/PKG-INFO
nimscommon.egg-info/SOURCES.txt
nimscommon.egg-info/dependency_links.txt
nimscommon.egg-info/not-zip-safe
nimscommon.egg-info/top_level.txt